phootonics_controller/__init__.py
phootonics_controller/api/app.py
phootonics_controller/base_controllers/admins
phootonics_controller/base_controllers/config.py
phootonics_controller/base_controllers/main_controller.py
phootonics_controller/base_controllers/stage_mock.py
phootonics_controller/base_controllers/stage_vcm.py
phootonics_controller/base_controllers/users
phootonics_controller/base_controllers/xc_controller.py
phootonics_controller/scripts/__init__.py
phootonics_controller/scripts/scan.py
phootonics_controller/tests/__init__.py
phootonics_controller/tests/phootonics_client.py
phootonics_controller/tests/test_adc.py
phootonics_controller/utils/__init__.py
phootonics_controller/utils/alparser.py
phootonics_controller/utils/ADC_converter/ADS1263.py
phootonics_controller/utils/ADC_converter/ads_config.py
phootonics_controller/utils/MR_E_2_Python_SDK/License.rtf
phootonics_controller/utils/MR_E_2_Python_SDK/optoMDC_documentation.lnk.lnk
phootonics_controller/utils/MR_E_2_Python_SDK/inflect/inflect.py
phootonics_controller/utils/MR_E_2_Python_SDK/optoKummenberg/__init__.py
phootonics_controller/utils/MR_E_2_Python_SDK/optoKummenberg/commands.py
phootonics_controller/utils/MR_E_2_Python_SDK/optoKummenberg/connections.py
phootonics_controller/utils/MR_E_2_Python_SDK/optoKummenberg/registers/ClassAbstracts.py
phootonics_controller/utils/MR_E_2_Python_SDK/optoKummenberg/registers/ControlStage.py
phootonics_controller/utils/MR_E_2_Python_SDK/optoKummenberg/registers/InputConditioning.py
phootonics_controller/utils/MR_E_2_Python_SDK/optoKummenberg/registers/InputStage.py
phootonics_controller/utils/MR_E_2_Python_SDK/optoKummenberg/registers/MiscSystems.py
phootonics_controller/utils/MR_E_2_Python_SDK/optoKummenberg/registers/OutputConditioning.py
phootonics_controller/utils/MR_E_2_Python_SDK/optoKummenberg/registers/OutputStage.py
phootonics_controller/utils/MR_E_2_Python_SDK/optoKummenberg/registers/__init__.py
phootonics_controller-5.4.2.dist-info/AUTHORS
phootonics_controller-5.4.2.dist-info/METADATA
phootonics_controller-5.4.2.dist-info/WHEEL
phootonics_controller-5.4.2.dist-info/entry_points.txt
phootonics_controller-5.4.2.dist-info/pbr.json
phootonics_controller-5.4.2.dist-info/top_level.txt
phootonics_controller-5.4.2.dist-info/RECORD
