Metadata-Version: 2.1
Name: phootonics-controller
Version: 5.4.2
Summary: UNKNOWN
Home-page: UNKNOWN
Author: olgare
License: Proprietary
Keywords: phootonics_controller
Platform: UNKNOWN
Classifier: Intended Audience :: Developers
Classifier: License :: Other/Proprietary License
Classifier: Natural Language :: English
Classifier: Programming Language :: Python :: 3
License-File: AUTHORS
Requires-Dist: setuptools (~=40.8.0)
Requires-Dist: spidev (~=3.5)
Requires-Dist: pyserial (~=3.4)
Requires-Dist: enum34 (~=1.1.10)
Requires-Dist: requests (~=2.21.0)
Requires-Dist: flask-restful
Requires-Dist: motor-apt
Requires-Dist: numpy
